fragselect/.DS_Store
fragselect/__init__.py
fragselect/cli.py
fragselect/config.py
fragselect/constants.py
fragselect/dataloader.py
fragselect/directlfq.py
fragselect/evaluation.py
fragselect/featureengineering.py
fragselect/loader.py
fragselect/loss.py
fragselect/ms1_features.py
fragselect/output.py
fragselect/performance_evalution.py
fragselect/preprocessing.py
fragselect/shared_state.py
fragselect/simulation.py
fragselect/utils.py
fragselect/var_model.py
fragselect/visualizer.py
fragselect-0.0.1.dist-info/LICENSE.txt
fragselect-0.0.1.dist-info/METADATA
fragselect-0.0.1.dist-info/WHEEL
fragselect-0.0.1.dist-info/entry_points.txt
fragselect-0.0.1.dist-info/top_level.txt
fragselect-0.0.1.dist-info/RECORD
